weave/__init__.py
weave/basket.py
weave/config.py
weave/mongo_loader.py
weave/pantry.py
weave/pantry_factory.py
weave/upload.py
weave/validate.py
weave/index/__init__.py
weave/index/create_index.py
weave/index/index_abc.py
weave/index/index_pandas.py
weave/index/index_sql.py
weave/index/index_sqlite.py
weave/index/list_baskets.py
weave/index/validate_basket.py
weave/tests/pytest_resources.py
weave/tests/test_basket.py
weave/tests/test_config.py
weave/tests/test_index.py
weave/tests/test_index_pandas.py
weave/tests/test_index_sql.py
weave/tests/test_index_sqlite.py
weave/tests/test_mongo_db.py
weave/tests/test_pantry.py
weave/tests/test_pantry_factory.py
weave/tests/test_pytest.py
weave/tests/test_uploader.py
weave/tests/test_validate.py
weave_db-1.15.4.dist-info/METADATA
weave_db-1.15.4.dist-info/WHEEL
weave_db-1.15.4.dist-info/top_level.txt
weave_db-1.15.4.dist-info/RECORD
