Metadata-Version: 2.4
Name: weave-db
Version: 1.15.4
Summary: Library to facilitate the creation and maintenance of complex data warehouses.
Home-page: https://github.com/309thEDDGE/weave
Author: 309thEDDGE
License: GNU General Public
Classifier: License :: OSI Approved :: GNU General Public License (GPL)
Classifier: Programming Language :: Python :: 3.13
Classifier: Operating System :: OS Independent
Requires-Python: >=3.10
Requires-Dist: pandas
Requires-Dist: s3fs
Requires-Dist: fsspec
Requires-Dist: jsonschema
Provides-Extra: extras
Requires-Dist: pymongo; extra == "extras"
Requires-Dist: psycopg2-binary; extra == "extras"
Requires-Dist: sqlalchemy; extra == "extras"
Dynamic: author
Dynamic: classifier
Dynamic: description
Dynamic: description-content-type
Dynamic: home-page
Dynamic: license
Dynamic: provides-extra
Dynamic: requires-dist
Dynamic: requires-python
Dynamic: summary
